gcp_duppla/__init__.py
gcp_duppla/bq.py
gcp_duppla/gcs.py
gcp_duppla/src/__init__.py
gcp_duppla/src/entities.py
gcp_duppla-0.0.6.dist-info/METADATA
gcp_duppla-0.0.6.dist-info/WHEEL
gcp_duppla-0.0.6.dist-info/top_level.txt
gcp_duppla-0.0.6.dist-info/RECORD
