Metadata-Version: 2.1
Name: gcp-duppla
Version: 0.0.6
Summary: A simpler version of GCP API
Author: Fernando Cortés
Author-email: <fcortes@pucp.edu.pe>
Keywords: python,gcp,bigquery,gcs,pandas
Classifier: Development Status :: 3 - Alpha
Classifier: Intended Audience :: Education
Classifier: Programming Language :: Python :: 3
Classifier: Operating System :: MacOS :: MacOS X
Classifier: Operating System :: Microsoft :: Windows
Classifier: Operating System :: Unix
